<pokedex><pokemon number="601" name="Klinklang"><description rank="0">Its red core functions as an energy tank. It fires the charged energy through its spikes into an area.</description><description rank="1">The gear with the red core is rotated at high speed for a rapid energy charge.</description><genders></genders><species>Gear</species><evolution pattern="5" position="2">599,600,601</evolution><formes><forme name="Klinklang" index="0"><images/><stats hp="40" attack="80" defense="100" specAttack=" 60" specDefense="60" speed="80"/><types>Steel</types><abilities>Minus,Plus</abilities><weakness type="Fire" mod="0"/><weakness type="Fighting" mod="0"/><weakness type="Ground" mod="0"/><height>0.6</height><weight>81.0</weight><formatted-height>0.6 m</formatted-height><formatted-weight>81.0 kg</formatted-weight></forme></formes></pokemon></pokedex>
