<pokedex><pokemon number="180" name="Flaaffy"><description rank="0">If its coat becomes fully charged with electricity, its tail lights up. It fires hair that zaps on impact.</description><genders>Male,Female</genders><species>Wool</species><evolution pattern="5" position="1">179,180,181</evolution><formes><forme name="Flaaffy" index="0"><images/><stats hp="60" attack="40" defense="40" specAttack=" 80" specDefense="40" speed="40"/><types>Electric</types><abilities>Static</abilities><weakness type="Ground" mod="0"/><height>0.8</height><weight>13.3</weight><formatted-height>0.8 m</formatted-height><formatted-weight>13.3 kg</formatted-weight></forme></formes></pokemon></pokedex>
